NetHyTech/__init__.py
nethytech-1.2.dist-info/LICENSE
nethytech-1.2.dist-info/METADATA
nethytech-1.2.dist-info/WHEEL
nethytech-1.2.dist-info/entry_points.txt
nethytech-1.2.dist-info/top_level.txt
nethytech-1.2.dist-info/RECORD
