Metadata-Version: 2.1
Name: nethytech
Version: 1.2
Summary: NethyTech: One of the finest automation toolkits crafted by Anubhav Chaturvedi, bringing you powerful real-time text monitoring, dynamic weather insights, file utilities, and seamless automation – all in one Python package.
Home-page: https://github.com/AnubhavChaturvedi-GitHub/NetHyTech-Package
Author: Anubhav Chaturvedi
Author-email: chaturvedianubhav520@gmail.com
License: MIT
Project-URL: Documentation, https://anubhav-chaturvedi.netlify.app/
Project-URL: Source, https://github.com/anubhav-chaturvedi/nethytech
Project-URL: Tracker, https://github.com/anubhav-chaturvedi/nethytech/issues
Classifier: Development Status :: 4 - Beta
Classifier: Intended Audience :: Developers
Classifier: License :: OSI Approved :: MIT License
Classifier: Programming Language :: Python :: 3.8
Classifier: Programming Language :: Python :: 3.9
Classifier: Programming Language :: Python :: 3.10
Classifier: Programming Language :: Python :: 3.11
Classifier: Programming Language :: Python :: 3.12
Classifier: Topic :: Software Development :: Libraries :: Python Modules
Requires-Python: >=3.8
License-File: LICENSE
Requires-Dist: selenium>=4.0.0
Requires-Dist: webdriver-manager>=3.8.0
